{
   "username":"medisetti.tejasurya@solverminds.com",
   "Vesselcode":"PMM",
   "speed":12,
   "version":1,
   "chartedpartyRefNo":"PMM MP 002 TMJ",
   "remarks":"",
   "Propelleraftmindraft":7.83,
   "Propellerfwdmindraft":4.328,
   "Schedule":[
      {
         "portcode":"AUNLT",
         "portname":"NEW CASTLE",
         "terminalcode":"",
         "currentport":"Y",
         "arrivaldate":"07/03/2023 00:00",
         "departuredate":"08/03/2023 12:00",
         "terminaltime":"1.5",
         "Portindex":1,
         "servicecode":"ABC",
         "voyageno":"0653",
         "bound":"N",
         "terminalTime":1.5,
         "shortportcode":"",
         "vesselName":"PIRIKA MOSIRI MARU",
         "portcolor":"238,68,68"
      },
      {
         "portcode":"AUGLT",
         "portname":"GRADSTONE",
         "terminalcode":"",
         "currentport":"N",
         "arrivaldate":"10/03/2023 01:30",
         "departuredate":"11/03/2023 13:30",
         "terminaltime":"1.5",
         "Portindex":2,
         "servicecode":"ABC",
         "voyageno":"0653",
         "bound":"N",
         "terminalTime":1.5,
         "shortportcode":"",
         "vesselName":"PIRIKA MOSIRI MARU",
         "portcolor":"59,14,221"
      },
      {
         "portcode":"JPKWS",
         "portname":"KAWASAKI",
         "terminalcode":"",
         "currentport":"N",
         "arrivaldate":"24/03/2023 22:30",
         "departuredate":"26/03/2023 10:30",
         "terminaltime":"1.5",
         "Portindex":3,
         "servicecode":"ABC",
         "voyageno":"0653",
         "bound":"N",
         "terminalTime":1.5,
         "shortportcode":"",
         "vesselName":"PIRIKA MOSIRI MARU",
         "portcolor":"0,153,0"
      },
      {
         "portcode":"JPFKY",
         "portname":"FUKUYAMA",
         "terminalcode":"",
         "currentport":"N",
         "arrivaldate":"28/03/2023 07:40",
         "departuredate":"29/03/2023 19:40",
         "terminaltime":"1.5",
         "Portindex":4,
         "servicecode":"ABC",
         "voyageno":"0653",
         "bound":"N",
         "terminalTime":1.5,
         "shortportcode":"",
         "vesselName":"PIRIKA MOSIRI MARU",
         "portcolor":"102,0,0"
      }
   ],
   "CargoDetails":[
      {
         "pol":"AUNLT",
         "polIdx":1,
         "pod":"JPFKY",
         "podIdx":4,
         "name":"coal",
         "grade":"A",
         "weight":30000,
         "stowagefactor":39.859,
         "maxdischarge":"N"
      },
      {
         "pol":"AUGLT",
         "polIdx":2,
         "pod":"JPKWS",
         "podIdx":3,
         "name":"COAL",
         "grade":"B",
         "weight":30000,
         "stowagefactor":40.845,
         "maxdischarge":"N"
      },
      {
         "pol":"AUGLT",
         "polIdx":2,
         "pod":"JPFKY",
         "podIdx":4,
         "name":"COAL",
         "grade":"B",
         "weight":30000,
         "stowagefactor":40.845,
         "maxdischarge":"N"
      }
   ],
   "Parameter":[
      {
         "pol":"AUNLT",
         "trim":3,
         "ballast":1,
         "deballast":1,
         "tankwt":0,
         "hogorsag":"Auto",
         "hogorsagvalue":35,
         "stress":1,
         "loadwaterline":"Summer Water Line (S)",
         "draft":12.882,
         "airdraft":48,
         "seaWaterDensity":1.023,
         "seaport":0,
         "draftlimit":14.2,
         "arrivalairdraft":48,
         "arrivalswdensity":1.023,
         "arrivaldraft":16,
         "NumberofHatchCovers":5,
         "airdraftHatchcover":30,
         "meandraft":0,
         "polidx":1,
         "SFValue":99,
         "BMValue":99,
         "hatchAirDraft":30
      },
      {
         "pol":"AUGLT",
         "trim":3,
         "ballast":1,
         "deballast":1,
         "tankwt":0,
         "hogorsag":"Auto",
         "hogorsagvalue":35,
         "stress":1,
         "loadwaterline":"Summer Water Line (S)",
         "draft":12.882,
         "airdraft":48,
         "seaWaterDensity":1.023,
         "seaport":0,
         "draftlimit":16,
         "arrivalairdraft":48,
         "arrivalswdensity":1.023,
         "arrivaldraft":16,
         "NumberofHatchCovers":5,
         "airdraftHatchcover":30,
         "meandraft":0,
         "polidx":2,
         "SFValue":99,
         "BMValue":99,
         "hatchAirDraft":30
      },
      {
         "pol":"JPKWS",
         "trim":3,
         "ballast":1,
         "deballast":1,
         "tankwt":0,
         "hogorsag":"Auto",
         "hogorsagvalue":35,
         "stress":1,
         "loadwaterline":"Summer Water Line (S)",
         "draft":12.882,
         "airdraft":48,
         "seaWaterDensity":1.023,
         "seaport":0,
         "draftlimit":16,
         "arrivalairdraft":48,
         "arrivalswdensity":1.023,
         "arrivaldraft":16,
         "NumberofHatchCovers":5,
         "airdraftHatchcover":30,
         "meandraft":0,
         "polidx":3,
         "SFValue":99,
         "BMValue":99,
         "hatchAirDraft":30
      },
      {
         "pol":"JPFKY",
         "trim":3,
         "ballast":1,
         "deballast":1,
         "tankwt":0,
         "hogorsag":"Auto",
         "hogorsagvalue":35,
         "stress":1,
         "loadwaterline":"Summer Water Line (S)",
         "draft":12.882,
         "airdraft":48,
         "seaWaterDensity":1.023,
         "seaport":0,
         "draftlimit":16,
         "arrivalairdraft":48,
         "arrivalswdensity":1.023,
         "arrivaldraft":16,
         "NumberofHatchCovers":5,
         "airdraftHatchcover":30,
         "meandraft":0,
         "polidx":4,
         "SFValue":99,
         "BMValue":99,
         "hatchAirDraft":30
      }
   ],
   "WaterBallast":[
      {
         "scenarioid":"PMM MP 002 TMJ",
         "port":"AUNLT",
         "portindex":1,
         "tankcategory":"WB",
         "tankname":"FORE PEAK TANK C",
         "volincube":0,
         "vesselcode":"PMM",
         "density":1.025,
         "capacity":3341,
         "weight":0,
         "lcglpp":218.62,
         "vcgbl":0,
         "tcgcl":0,
         "fsm":21.1,
         "select":true,
         "maxper":100,
         "partialyfilled":false,
         "fullyfilled":false,
         "unpumpableweight":0,
         "holdtank":"N",
         "bmax":"false",
         "sounding":0,
         "volinpercent":0
      },
      {
         "scenarioid":"PMM MP 002 TMJ",
         "port":"AUNLT",
         "portindex":1,
         "tankcategory":"WB",
         "tankname":"NO.1 WATER BALLAST TANK (P)",
         "volincube":0,
         "vesselcode":"PMM",
         "density":1.025,
         "capacity":2608.9,
         "weight":0,
         "lcglpp":195.53,
         "vcgbl":0,
         "tcgcl":-7.54,
         "fsm":9921.5,
         "select":true,
         "maxper":100,
         "partialyfilled":false,
         "fullyfilled":false,
         "unpumpableweight":0,
         "holdtank":"N",
         "bmax":"false",
         "sounding":0,
         "volinpercent":0
      },
      {
         "scenarioid":"PMM MP 002 TMJ",
         "port":"AUNLT",
         "portindex":1,
         "tankcategory":"WB",
         "tankname":"NO.1 WATER BALLAST TANK (S)",
         "volincube":0,
         "vesselcode":"PMM",
         "density":1.025,
         "capacity":2608.9,
         "weight":0,
         "lcglpp":195.53,
         "vcgbl":0,
         "tcgcl":7.54,
         "fsm":9921.5,
         "select":true,
         "maxper":100,
         "partialyfilled":false,
         "fullyfilled":false,
         "unpumpableweight":0,
         "holdtank":"N",
         "bmax":"false",
         "sounding":0,
         "volinpercent":0
      },
      {
         "scenarioid":"PMM MP 002 TMJ",
         "port":"AUNLT",
         "portindex":1,
         "tankcategory":"WB",
         "tankname":"NO.2 WATER BALLAST TANK (P)",
         "volincube":0,
         "vesselcode":"PMM",
         "density":1.025,
         "capacity":3576.8,
         "weight":0,
         "lcglpp":161.52,
         "vcgbl":0,
         "tcgcl":-10.03,
         "fsm":24309,
         "select":true,
         "maxper":100,
         "partialyfilled":false,
         "fullyfilled":false,
         "unpumpableweight":0,
         "holdtank":"N",
         "bmax":"false",
         "sounding":0,
         "volinpercent":0
      },
      {
         "scenarioid":"PMM MP 002 TMJ",
         "port":"AUNLT",
         "portindex":1,
         "tankcategory":"WB",
         "tankname":"NO.2 WATER BALLAST TANK (S)",
         "volincube":0,
         "vesselcode":"PMM",
         "density":1.025,
         "capacity":3576.8,
         "weight":0,
         "lcglpp":161.52,
         "vcgbl":0,
         "tcgcl":10.03,
         "fsm":24309,
         "select":true,
         "maxper":100,
         "partialyfilled":false,
         "fullyfilled":false,
         "unpumpableweight":0,
         "holdtank":"N",
         "bmax":"false",
         "sounding":0,
         "volinpercent":0
      },
      {
         "scenarioid":"PMM MP 002 TMJ",
         "port":"AUNLT",
         "portindex":1,
         "tankcategory":"WB",
         "tankname":"NO.3 WATER BALLAST TANK (P)",
         "volincube":0,
         "vesselcode":"PMM",
         "density":1.025,
         "capacity":3330.3,
         "weight":0,
         "lcglpp":124.58,
         "vcgbl":0,
         "tcgcl":-10.09,
         "fsm":23170.6,
         "select":true,
         "maxper":100,
         "partialyfilled":false,
         "fullyfilled":false,
         "unpumpableweight":0,
         "holdtank":"N",
         "bmax":"false",
         "sounding":0,
         "volinpercent":0
      },
      {
         "scenarioid":"PMM MP 002 TMJ",
         "port":"AUNLT",
         "portindex":1,
         "tankcategory":"WB",
         "tankname":"NO.3 WATER BALLAST TANK (S)",
         "volincube":0,
         "vesselcode":"PMM",
         "density":1.025,
         "capacity":3330.3,
         "weight":0,
         "lcglpp":124.58,
         "vcgbl":0,
         "tcgcl":10.09,
         "fsm":23170.6,
         "select":true,
         "maxper":100,
         "partialyfilled":false,
         "fullyfilled":false,
         "unpumpableweight":0,
         "holdtank":"N",
         "bmax":"false",
         "sounding":0,
         "volinpercent":0
      },
      {
         "scenarioid":"PMM MP 002 TMJ",
         "port":"AUNLT",
         "portindex":1,
         "tankcategory":"WB",
         "tankname":"NO.4 WATER BALLAST TANK (P)",
         "volincube":0,
         "vesselcode":"PMM",
         "density":1.025,
         "capacity":2734.3,
         "weight":0,
         "lcglpp":87.86,
         "vcgbl":0,
         "tcgcl":-9.85,
         "fsm":23005.4,
         "select":true,
         "maxper":100,
         "partialyfilled":false,
         "fullyfilled":false,
         "unpumpableweight":0,
         "holdtank":"N",
         "bmax":"false",
         "sounding":0,
         "volinpercent":0
      },
      {
         "scenarioid":"PMM MP 002 TMJ",
         "port":"AUNLT",
         "portindex":1,
         "tankcategory":"WB",
         "tankname":"NO.4 WATER BALLAST TANK (S)",
         "volincube":0,
         "vesselcode":"PMM",
         "density":1.025,
         "capacity":2734.3,
         "weight":0,
         "lcglpp":87.86,
         "vcgbl":0,
         "tcgcl":9.85,
         "fsm":23005.4,
         "select":true,
         "maxper":100,
         "partialyfilled":false,
         "fullyfilled":false,
         "unpumpableweight":0,
         "holdtank":"N",
         "bmax":"false",
         "sounding":0,
         "volinpercent":0
      },
      {
         "scenarioid":"PMM MP 002 TMJ",
         "port":"AUNLT",
         "portindex":1,
         "tankcategory":"WB",
         "tankname":"NO.5 WATER BALLAST TANK (P)",
         "volincube":0,
         "vesselcode":"PMM",
         "density":1.025,
         "capacity":2119.7,
         "weight":0,
         "lcglpp":53.6,
         "vcgbl":0,
         "tcgcl":-6.28,
         "fsm":6281.9,
         "select":true,
         "maxper":100,
         "partialyfilled":false,
         "fullyfilled":false,
         "unpumpableweight":0,
         "holdtank":"N",
         "bmax":"false",
         "sounding":0,
         "volinpercent":0
      },
      {
         "scenarioid":"PMM MP 002 TMJ",
         "port":"AUNLT",
         "portindex":1,
         "tankcategory":"WB",
         "tankname":"NO.5 WATER BALLAST TANK (S)",
         "volincube":0,
         "vesselcode":"PMM",
         "density":1.025,
         "capacity":2277.3,
         "weight":0,
         "lcglpp":53.41,
         "vcgbl":0,
         "tcgcl":6.25,
         "fsm":6338.8,
         "select":true,
         "maxper":100,
         "partialyfilled":false,
         "fullyfilled":false,
         "unpumpableweight":0,
         "holdtank":"N",
         "bmax":"false",
         "sounding":0,
         "volinpercent":0
      },
      {
         "scenarioid":"PMM MP 002 TMJ",
         "port":"AUNLT",
         "portindex":1,
         "tankcategory":"WB",
         "tankname":"NO.5 T. S. T. /COLL. TANK (P)",
         "volincube":0,
         "vesselcode":"PMM",
         "density":1.025,
         "capacity":519,
         "weight":0,
         "lcglpp":41.79,
         "vcgbl":12.32,
         "tcgcl":-20.76,
         "fsm":0.1,
         "select":true,
         "maxper":100,
         "partialyfilled":false,
         "fullyfilled":false,
         "unpumpableweight":0,
         "holdtank":"N",
         "bmax":"false",
         "sounding":0,
         "volinpercent":0
      },
      {
         "scenarioid":"PMM MP 002 TMJ",
         "port":"AUNLT",
         "portindex":1,
         "tankcategory":"WB",
         "tankname":"NO.5 T. S. T. /COLL. TANK (S)",
         "volincube":0,
         "vesselcode":"PMM",
         "density":1.025,
         "capacity":519,
         "weight":0,
         "lcglpp":41.79,
         "vcgbl":12.32,
         "tcgcl":20.76,
         "fsm":0.1,
         "select":true,
         "maxper":100,
         "partialyfilled":false,
         "fullyfilled":false,
         "unpumpableweight":0,
         "holdtank":"N",
         "bmax":"false",
         "sounding":0,
         "volinpercent":0
      },
      {
         "scenarioid":"PMM MP 002 TMJ",
         "port":"AUNLT",
         "portindex":1,
         "tankcategory":"WB",
         "tankname":"AFT PEAK TANK C",
         "volincube":0,
         "vesselcode":"PMM",
         "density":1.025,
         "capacity":1732.1,
         "weight":0,
         "lcglpp":9.19,
         "vcgbl":7.93,
         "tcgcl":0,
         "fsm":0.1,
         "select":true,
         "maxper":100,
         "partialyfilled":false,
         "fullyfilled":false,
         "unpumpableweight":0,
         "holdtank":"N",
         "bmax":"false",
         "sounding":0,
         "volinpercent":0
      },
      {
         "scenarioid":"PMM MP 002 TMJ",
         "port":"AUNLT",
         "portindex":1,
         "tankcategory":"WB",
         "tankname":"NO.3 HOLD (W.B)",
         "volincube":0,
         "vesselcode":"PMM",
         "density":1.025,
         "capacity":21509,
         "weight":0,
         "lcglpp":124.58,
         "vcgbl":2.07,
         "tcgcl":0,
         "fsm":85795.7,
         "select":true,
         "maxper":100,
         "partialyfilled":false,
         "fullyfilled":false,
         "unpumpableweight":0,
         "holdtank":"Y",
         "bmax":"false",
         "sounding":0,
         "volinpercent":0
      },
      {
         "scenarioid":"PMM MP 002 TMJ",
         "port":"AUGLT",
         "portindex":2,
         "tankcategory":"WB",
         "tankname":"FORE PEAK TANK C",
         "volincube":0,
         "vesselcode":"PMM",
         "density":1.025,
         "capacity":3341,
         "weight":0,
         "lcglpp":218.62,
         "vcgbl":0,
         "tcgcl":0,
         "fsm":21.1,
         "select":true,
         "maxper":100,
         "partialyfilled":false,
         "fullyfilled":false,
         "unpumpableweight":0,
         "holdtank":"N",
         "bmax":"false",
         "sounding":0,
         "volinpercent":0
      },
      {
         "scenarioid":"PMM MP 002 TMJ",
         "port":"AUGLT",
         "portindex":2,
         "tankcategory":"WB",
         "tankname":"NO.1 WATER BALLAST TANK (P)",
         "volincube":0,
         "vesselcode":"PMM",
         "density":1.025,
         "capacity":2608.9,
         "weight":0,
         "lcglpp":195.53,
         "vcgbl":0,
         "tcgcl":-7.54,
         "fsm":9921.5,
         "select":true,
         "maxper":100,
         "partialyfilled":false,
         "fullyfilled":false,
         "unpumpableweight":0,
         "holdtank":"N",
         "bmax":"false",
         "sounding":0,
         "volinpercent":0
      },
      {
         "scenarioid":"PMM MP 002 TMJ",
         "port":"AUGLT",
         "portindex":2,
         "tankcategory":"WB",
         "tankname":"NO.1 WATER BALLAST TANK (S)",
         "volincube":0,
         "vesselcode":"PMM",
         "density":1.025,
         "capacity":2608.9,
         "weight":0,
         "lcglpp":195.53,
         "vcgbl":0,
         "tcgcl":7.54,
         "fsm":9921.5,
         "select":true,
         "maxper":100,
         "partialyfilled":false,
         "fullyfilled":false,
         "unpumpableweight":0,
         "holdtank":"N",
         "bmax":"false",
         "sounding":0,
         "volinpercent":0
      },
      {
         "scenarioid":"PMM MP 002 TMJ",
         "port":"AUGLT",
         "portindex":2,
         "tankcategory":"WB",
         "tankname":"NO.2 WATER BALLAST TANK (P)",
         "volincube":0,
         "vesselcode":"PMM",
         "density":1.025,
         "capacity":3576.8,
         "weight":0,
         "lcglpp":161.52,
         "vcgbl":0,
         "tcgcl":-10.03,
         "fsm":24309,
         "select":true,
         "maxper":100,
         "partialyfilled":false,
         "fullyfilled":false,
         "unpumpableweight":0,
         "holdtank":"N",
         "bmax":"false",
         "sounding":0,
         "volinpercent":0
      },
      {
         "scenarioid":"PMM MP 002 TMJ",
         "port":"AUGLT",
         "portindex":2,
         "tankcategory":"WB",
         "tankname":"NO.2 WATER BALLAST TANK (S)",
         "volincube":0,
         "vesselcode":"PMM",
         "density":1.025,
         "capacity":3576.8,
         "weight":0,
         "lcglpp":161.52,
         "vcgbl":0,
         "tcgcl":10.03,
         "fsm":24309,
         "select":true,
         "maxper":100,
         "partialyfilled":false,
         "fullyfilled":false,
         "unpumpableweight":0,
         "holdtank":"N",
         "bmax":"false",
         "sounding":0,
         "volinpercent":0
      },
      {
         "scenarioid":"PMM MP 002 TMJ",
         "port":"AUGLT",
         "portindex":2,
         "tankcategory":"WB",
         "tankname":"NO.3 WATER BALLAST TANK (P)",
         "volincube":0,
         "vesselcode":"PMM",
         "density":1.025,
         "capacity":3330.3,
         "weight":0,
         "lcglpp":124.58,
         "vcgbl":0,
         "tcgcl":-10.09,
         "fsm":23170.6,
         "select":true,
         "maxper":100,
         "partialyfilled":false,
         "fullyfilled":false,
         "unpumpableweight":0,
         "holdtank":"N",
         "bmax":"false",
         "sounding":0,
         "volinpercent":0
      },
      {
         "scenarioid":"PMM MP 002 TMJ",
         "port":"AUGLT",
         "portindex":2,
         "tankcategory":"WB",
         "tankname":"NO.3 WATER BALLAST TANK (S)",
         "volincube":0,
         "vesselcode":"PMM",
         "density":1.025,
         "capacity":3330.3,
         "weight":0,
         "lcglpp":124.58,
         "vcgbl":0,
         "tcgcl":10.09,
         "fsm":23170.6,
         "select":true,
         "maxper":100,
         "partialyfilled":false,
         "fullyfilled":false,
         "unpumpableweight":0,
         "holdtank":"N",
         "bmax":"false",
         "sounding":0,
         "volinpercent":0
      },
      {
         "scenarioid":"PMM MP 002 TMJ",
         "port":"AUGLT",
         "portindex":2,
         "tankcategory":"WB",
         "tankname":"NO.4 WATER BALLAST TANK (P)",
         "volincube":0,
         "vesselcode":"PMM",
         "density":1.025,
         "capacity":2734.3,
         "weight":0,
         "lcglpp":87.86,
         "vcgbl":0,
         "tcgcl":-9.85,
         "fsm":23005.4,
         "select":true,
         "maxper":100,
         "partialyfilled":false,
         "fullyfilled":false,
         "unpumpableweight":0,
         "holdtank":"N",
         "bmax":"false",
         "sounding":0,
         "volinpercent":0
      },
      {
         "scenarioid":"PMM MP 002 TMJ",
         "port":"AUGLT",
         "portindex":2,
         "tankcategory":"WB",
         "tankname":"NO.4 WATER BALLAST TANK (S)",
         "volincube":0,
         "vesselcode":"PMM",
         "density":1.025,
         "capacity":2734.3,
         "weight":0,
         "lcglpp":87.86,
         "vcgbl":0,
         "tcgcl":9.85,
         "fsm":23005.4,
         "select":true,
         "maxper":100,
         "partialyfilled":false,
         "fullyfilled":false,
         "unpumpableweight":0,
         "holdtank":"N",
         "bmax":"false",
         "sounding":0,
         "volinpercent":0
      },
      {
         "scenarioid":"PMM MP 002 TMJ",
         "port":"AUGLT",
         "portindex":2,
         "tankcategory":"WB",
         "tankname":"NO.5 WATER BALLAST TANK (P)",
         "volincube":0,
         "vesselcode":"PMM",
         "density":1.025,
         "capacity":2119.7,
         "weight":0,
         "lcglpp":53.6,
         "vcgbl":0,
         "tcgcl":-6.28,
         "fsm":6281.9,
         "select":true,
         "maxper":100,
         "partialyfilled":false,
         "fullyfilled":false,
         "unpumpableweight":0,
         "holdtank":"N",
         "bmax":"false",
         "sounding":0,
         "volinpercent":0
      },
      {
         "scenarioid":"PMM MP 002 TMJ",
         "port":"AUGLT",
         "portindex":2,
         "tankcategory":"WB",
         "tankname":"NO.5 WATER BALLAST TANK (S)",
         "volincube":0,
         "vesselcode":"PMM",
         "density":1.025,
         "capacity":2277.3,
         "weight":0,
         "lcglpp":53.41,
         "vcgbl":0,
         "tcgcl":6.25,
         "fsm":6338.8,
         "select":true,
         "maxper":100,
         "partialyfilled":false,
         "fullyfilled":false,
         "unpumpableweight":0,
         "holdtank":"N",
         "bmax":"false",
         "sounding":0,
         "volinpercent":0
      },
      {
         "scenarioid":"PMM MP 002 TMJ",
         "port":"AUGLT",
         "portindex":2,
         "tankcategory":"WB",
         "tankname":"NO.5 T. S. T. /COLL. TANK (P)",
         "volincube":0,
         "vesselcode":"PMM",
         "density":1.025,
         "capacity":519,
         "weight":0,
         "lcglpp":41.79,
         "vcgbl":12.32,
         "tcgcl":-20.76,
         "fsm":0.1,
         "select":true,
         "maxper":100,
         "partialyfilled":false,
         "fullyfilled":false,
         "unpumpableweight":0,
         "holdtank":"N",
         "bmax":"false",
         "sounding":0,
         "volinpercent":0
      },
      {
         "scenarioid":"PMM MP 002 TMJ",
         "port":"AUGLT",
         "portindex":2,
         "tankcategory":"WB",
         "tankname":"NO.5 T. S. T. /COLL. TANK (S)",
         "volincube":0,
         "vesselcode":"PMM",
         "density":1.025,
         "capacity":519,
         "weight":0,
         "lcglpp":41.79,
         "vcgbl":12.32,
         "tcgcl":20.76,
         "fsm":0.1,
         "select":true,
         "maxper":100,
         "partialyfilled":false,
         "fullyfilled":false,
         "unpumpableweight":0,
         "holdtank":"N",
         "bmax":"false",
         "sounding":0,
         "volinpercent":0
      },
      {
         "scenarioid":"PMM MP 002 TMJ",
         "port":"AUGLT",
         "portindex":2,
         "tankcategory":"WB",
         "tankname":"AFT PEAK TANK C",
         "volincube":0,
         "vesselcode":"PMM",
         "density":1.025,
         "capacity":1732.1,
         "weight":0,
         "lcglpp":9.19,
         "vcgbl":7.93,
         "tcgcl":0,
         "fsm":0.1,
         "select":true,
         "maxper":100,
         "partialyfilled":false,
         "fullyfilled":false,
         "unpumpableweight":0,
         "holdtank":"N",
         "bmax":"false",
         "sounding":0,
         "volinpercent":0
      },
      {
         "scenarioid":"PMM MP 002 TMJ",
         "port":"AUGLT",
         "portindex":2,
         "tankcategory":"WB",
         "tankname":"NO.3 HOLD (W.B)",
         "volincube":0,
         "vesselcode":"PMM",
         "density":1.025,
         "capacity":21509,
         "weight":0,
         "lcglpp":124.58,
         "vcgbl":2.07,
         "tcgcl":0,
         "fsm":85795.7,
         "select":true,
         "maxper":100,
         "partialyfilled":false,
         "fullyfilled":false,
         "unpumpableweight":0,
         "holdtank":"Y",
         "bmax":"false",
         "sounding":0,
         "volinpercent":0
      },
      {
         "scenarioid":"PMM MP 002 TMJ",
         "port":"JPKWS",
         "portindex":3,
         "tankcategory":"WB",
         "tankname":"FORE PEAK TANK C",
         "volincube":0,
         "vesselcode":"PMM",
         "density":1.025,
         "capacity":3341,
         "weight":0,
         "lcglpp":218.62,
         "vcgbl":0,
         "tcgcl":0,
         "fsm":21.1,
         "select":true,
         "maxper":100,
         "partialyfilled":false,
         "fullyfilled":false,
         "unpumpableweight":0,
         "holdtank":"N",
         "bmax":"false",
         "sounding":0,
         "volinpercent":0
      },
      {
         "scenarioid":"PMM MP 002 TMJ",
         "port":"JPKWS",
         "portindex":3,
         "tankcategory":"WB",
         "tankname":"NO.1 WATER BALLAST TANK (P)",
         "volincube":0,
         "vesselcode":"PMM",
         "density":1.025,
         "capacity":2608.9,
         "weight":0,
         "lcglpp":195.53,
         "vcgbl":0,
         "tcgcl":-7.54,
         "fsm":9921.5,
         "select":true,
         "maxper":100,
         "partialyfilled":false,
         "fullyfilled":false,
         "unpumpableweight":0,
         "holdtank":"N",
         "bmax":"false",
         "sounding":0,
         "volinpercent":0
      },
      {
         "scenarioid":"PMM MP 002 TMJ",
         "port":"JPKWS",
         "portindex":3,
         "tankcategory":"WB",
         "tankname":"NO.1 WATER BALLAST TANK (S)",
         "volincube":0,
         "vesselcode":"PMM",
         "density":1.025,
         "capacity":2608.9,
         "weight":0,
         "lcglpp":195.53,
         "vcgbl":0,
         "tcgcl":7.54,
         "fsm":9921.5,
         "select":true,
         "maxper":100,
         "partialyfilled":false,
         "fullyfilled":false,
         "unpumpableweight":0,
         "holdtank":"N",
         "bmax":"false",
         "sounding":0,
         "volinpercent":0
      },
      {
         "scenarioid":"PMM MP 002 TMJ",
         "port":"JPKWS",
         "portindex":3,
         "tankcategory":"WB",
         "tankname":"NO.2 WATER BALLAST TANK (P)",
         "volincube":0,
         "vesselcode":"PMM",
         "density":1.025,
         "capacity":3576.8,
         "weight":0,
         "lcglpp":161.52,
         "vcgbl":0,
         "tcgcl":-10.03,
         "fsm":24309,
         "select":true,
         "maxper":100,
         "partialyfilled":false,
         "fullyfilled":false,
         "unpumpableweight":0,
         "holdtank":"N",
         "bmax":"false",
         "sounding":0,
         "volinpercent":0
      },
      {
         "scenarioid":"PMM MP 002 TMJ",
         "port":"JPKWS",
         "portindex":3,
         "tankcategory":"WB",
         "tankname":"NO.2 WATER BALLAST TANK (S)",
         "volincube":0,
         "vesselcode":"PMM",
         "density":1.025,
         "capacity":3576.8,
         "weight":0,
         "lcglpp":161.52,
         "vcgbl":0,
         "tcgcl":10.03,
         "fsm":24309,
         "select":true,
         "maxper":100,
         "partialyfilled":false,
         "fullyfilled":false,
         "unpumpableweight":0,
         "holdtank":"N",
         "bmax":"false",
         "sounding":0,
         "volinpercent":0
      },
      {
         "scenarioid":"PMM MP 002 TMJ",
         "port":"JPKWS",
         "portindex":3,
         "tankcategory":"WB",
         "tankname":"NO.3 WATER BALLAST TANK (P)",
         "volincube":0,
         "vesselcode":"PMM",
         "density":1.025,
         "capacity":3330.3,
         "weight":0,
         "lcglpp":124.58,
         "vcgbl":0,
         "tcgcl":-10.09,
         "fsm":23170.6,
         "select":true,
         "maxper":100,
         "partialyfilled":false,
         "fullyfilled":false,
         "unpumpableweight":0,
         "holdtank":"N",
         "bmax":"false",
         "sounding":0,
         "volinpercent":0
      },
      {
         "scenarioid":"PMM MP 002 TMJ",
         "port":"JPKWS",
         "portindex":3,
         "tankcategory":"WB",
         "tankname":"NO.3 WATER BALLAST TANK (S)",
         "volincube":0,
         "vesselcode":"PMM",
         "density":1.025,
         "capacity":3330.3,
         "weight":0,
         "lcglpp":124.58,
         "vcgbl":0,
         "tcgcl":10.09,
         "fsm":23170.6,
         "select":true,
         "maxper":100,
         "partialyfilled":false,
         "fullyfilled":false,
         "unpumpableweight":0,
         "holdtank":"N",
         "bmax":"false",
         "sounding":0,
         "volinpercent":0
      },
      {
         "scenarioid":"PMM MP 002 TMJ",
         "port":"JPKWS",
         "portindex":3,
         "tankcategory":"WB",
         "tankname":"NO.4 WATER BALLAST TANK (P)",
         "volincube":0,
         "vesselcode":"PMM",
         "density":1.025,
         "capacity":2734.3,
         "weight":0,
         "lcglpp":87.86,
         "vcgbl":0,
         "tcgcl":-9.85,
         "fsm":23005.4,
         "select":true,
         "maxper":100,
         "partialyfilled":false,
         "fullyfilled":false,
         "unpumpableweight":0,
         "holdtank":"N",
         "bmax":"false",
         "sounding":0,
         "volinpercent":0
      },
      {
         "scenarioid":"PMM MP 002 TMJ",
         "port":"JPKWS",
         "portindex":3,
         "tankcategory":"WB",
         "tankname":"NO.4 WATER BALLAST TANK (S)",
         "volincube":0,
         "vesselcode":"PMM",
         "density":1.025,
         "capacity":2734.3,
         "weight":0,
         "lcglpp":87.86,
         "vcgbl":0,
         "tcgcl":9.85,
         "fsm":23005.4,
         "select":true,
         "maxper":100,
         "partialyfilled":false,
         "fullyfilled":false,
         "unpumpableweight":0,
         "holdtank":"N",
         "bmax":"false",
         "sounding":0,
         "volinpercent":0
      },
      {
         "scenarioid":"PMM MP 002 TMJ",
         "port":"JPKWS",
         "portindex":3,
         "tankcategory":"WB",
         "tankname":"NO.5 WATER BALLAST TANK (P)",
         "volincube":0,
         "vesselcode":"PMM",
         "density":1.025,
         "capacity":2119.7,
         "weight":0,
         "lcglpp":53.6,
         "vcgbl":0,
         "tcgcl":-6.28,
         "fsm":6281.9,
         "select":true,
         "maxper":100,
         "partialyfilled":false,
         "fullyfilled":false,
         "unpumpableweight":0,
         "holdtank":"N",
         "bmax":"false",
         "sounding":0,
         "volinpercent":0
      },
      {
         "scenarioid":"PMM MP 002 TMJ",
         "port":"JPKWS",
         "portindex":3,
         "tankcategory":"WB",
         "tankname":"NO.5 WATER BALLAST TANK (S)",
         "volincube":0,
         "vesselcode":"PMM",
         "density":1.025,
         "capacity":2277.3,
         "weight":0,
         "lcglpp":53.41,
         "vcgbl":0,
         "tcgcl":6.25,
         "fsm":6338.8,
         "select":true,
         "maxper":100,
         "partialyfilled":false,
         "fullyfilled":false,
         "unpumpableweight":0,
         "holdtank":"N",
         "bmax":"false",
         "sounding":0,
         "volinpercent":0
      },
      {
         "scenarioid":"PMM MP 002 TMJ",
         "port":"JPKWS",
         "portindex":3,
         "tankcategory":"WB",
         "tankname":"NO.5 T. S. T. /COLL. TANK (P)",
         "volincube":0,
         "vesselcode":"PMM",
         "density":1.025,
         "capacity":519,
         "weight":0,
         "lcglpp":41.79,
         "vcgbl":12.32,
         "tcgcl":-20.76,
         "fsm":0.1,
         "select":true,
         "maxper":100,
         "partialyfilled":false,
         "fullyfilled":false,
         "unpumpableweight":0,
         "holdtank":"N",
         "bmax":"false",
         "sounding":0,
         "volinpercent":0
      },
      {
         "scenarioid":"PMM MP 002 TMJ",
         "port":"JPKWS",
         "portindex":3,
         "tankcategory":"WB",
         "tankname":"NO.5 T. S. T. /COLL. TANK (S)",
         "volincube":0,
         "vesselcode":"PMM",
         "density":1.025,
         "capacity":519,
         "weight":0,
         "lcglpp":41.79,
         "vcgbl":12.32,
         "tcgcl":20.76,
         "fsm":0.1,
         "select":true,
         "maxper":100,
         "partialyfilled":false,
         "fullyfilled":false,
         "unpumpableweight":0,
         "holdtank":"N",
         "bmax":"false",
         "sounding":0,
         "volinpercent":0
      },
      {
         "scenarioid":"PMM MP 002 TMJ",
         "port":"JPKWS",
         "portindex":3,
         "tankcategory":"WB",
         "tankname":"AFT PEAK TANK C",
         "volincube":0,
         "vesselcode":"PMM",
         "density":1.025,
         "capacity":1732.1,
         "weight":0,
         "lcglpp":9.19,
         "vcgbl":7.93,
         "tcgcl":0,
         "fsm":0.1,
         "select":true,
         "maxper":100,
         "partialyfilled":false,
         "fullyfilled":false,
         "unpumpableweight":0,
         "holdtank":"N",
         "bmax":"false",
         "sounding":0,
         "volinpercent":0
      },
      {
         "scenarioid":"PMM MP 002 TMJ",
         "port":"JPKWS",
         "portindex":3,
         "tankcategory":"WB",
         "tankname":"NO.3 HOLD (W.B)",
         "volincube":0,
         "vesselcode":"PMM",
         "density":1.025,
         "capacity":21509,
         "weight":0,
         "lcglpp":124.58,
         "vcgbl":2.07,
         "tcgcl":0,
         "fsm":85795.7,
         "select":true,
         "maxper":100,
         "partialyfilled":false,
         "fullyfilled":false,
         "unpumpableweight":0,
         "holdtank":"Y",
         "bmax":"false",
         "sounding":0,
         "volinpercent":0
      },
      {
         "scenarioid":"PMM MP 002 TMJ",
         "port":"JPFKY",
         "portindex":4,
         "tankcategory":"WB",
         "tankname":"FORE PEAK TANK C",
         "volincube":0,
         "vesselcode":"PMM",
         "density":1.025,
         "capacity":3341,
         "weight":0,
         "lcglpp":218.62,
         "vcgbl":0,
         "tcgcl":0,
         "fsm":21.1,
         "select":true,
         "maxper":100,
         "partialyfilled":false,
         "fullyfilled":false,
         "unpumpableweight":0,
         "holdtank":"N",
         "bmax":"false",
         "sounding":0,
         "volinpercent":0
      },
      {
         "scenarioid":"PMM MP 002 TMJ",
         "port":"JPFKY",
         "portindex":4,
         "tankcategory":"WB",
         "tankname":"NO.1 WATER BALLAST TANK (P)",
         "volincube":0,
         "vesselcode":"PMM",
         "density":1.025,
         "capacity":2608.9,
         "weight":0,
         "lcglpp":195.53,
         "vcgbl":0,
         "tcgcl":-7.54,
         "fsm":9921.5,
         "select":true,
         "maxper":100,
         "partialyfilled":false,
         "fullyfilled":false,
         "unpumpableweight":0,
         "holdtank":"N",
         "bmax":"false",
         "sounding":0,
         "volinpercent":0
      },
      {
         "scenarioid":"PMM MP 002 TMJ",
         "port":"JPFKY",
         "portindex":4,
         "tankcategory":"WB",
         "tankname":"NO.1 WATER BALLAST TANK (S)",
         "volincube":0,
         "vesselcode":"PMM",
         "density":1.025,
         "capacity":2608.9,
         "weight":0,
         "lcglpp":195.53,
         "vcgbl":0,
         "tcgcl":7.54,
         "fsm":9921.5,
         "select":true,
         "maxper":100,
         "partialyfilled":false,
         "fullyfilled":false,
         "unpumpableweight":0,
         "holdtank":"N",
         "bmax":"false",
         "sounding":0,
         "volinpercent":0
      },
      {
         "scenarioid":"PMM MP 002 TMJ",
         "port":"JPFKY",
         "portindex":4,
         "tankcategory":"WB",
         "tankname":"NO.2 WATER BALLAST TANK (P)",
         "volincube":0,
         "vesselcode":"PMM",
         "density":1.025,
         "capacity":3576.8,
         "weight":0,
         "lcglpp":161.52,
         "vcgbl":0,
         "tcgcl":-10.03,
         "fsm":24309,
         "select":true,
         "maxper":100,
         "partialyfilled":false,
         "fullyfilled":false,
         "unpumpableweight":0,
         "holdtank":"N",
         "bmax":"false",
         "sounding":0,
         "volinpercent":0
      },
      {
         "scenarioid":"PMM MP 002 TMJ",
         "port":"JPFKY",
         "portindex":4,
         "tankcategory":"WB",
         "tankname":"NO.2 WATER BALLAST TANK (S)",
         "volincube":0,
         "vesselcode":"PMM",
         "density":1.025,
         "capacity":3576.8,
         "weight":0,
         "lcglpp":161.52,
         "vcgbl":0,
         "tcgcl":10.03,
         "fsm":24309,
         "select":true,
         "maxper":100,
         "partialyfilled":false,
         "fullyfilled":false,
         "unpumpableweight":0,
         "holdtank":"N",
         "bmax":"false",
         "sounding":0,
         "volinpercent":0
      },
      {
         "scenarioid":"PMM MP 002 TMJ",
         "port":"JPFKY",
         "portindex":4,
         "tankcategory":"WB",
         "tankname":"NO.3 WATER BALLAST TANK (P)",
         "volincube":0,
         "vesselcode":"PMM",
         "density":1.025,
         "capacity":3330.3,
         "weight":0,
         "lcglpp":124.58,
         "vcgbl":0,
         "tcgcl":-10.09,
         "fsm":23170.6,
         "select":true,
         "maxper":100,
         "partialyfilled":false,
         "fullyfilled":false,
         "unpumpableweight":0,
         "holdtank":"N",
         "bmax":"false",
         "sounding":0,
         "volinpercent":0
      },
      {
         "scenarioid":"PMM MP 002 TMJ",
         "port":"JPFKY",
         "portindex":4,
         "tankcategory":"WB",
         "tankname":"NO.3 WATER BALLAST TANK (S)",
         "volincube":0,
         "vesselcode":"PMM",
         "density":1.025,
         "capacity":3330.3,
         "weight":0,
         "lcglpp":124.58,
         "vcgbl":0,
         "tcgcl":10.09,
         "fsm":23170.6,
         "select":true,
         "maxper":100,
         "partialyfilled":false,
         "fullyfilled":false,
         "unpumpableweight":0,
         "holdtank":"N",
         "bmax":"false",
         "sounding":0,
         "volinpercent":0
      },
      {
         "scenarioid":"PMM MP 002 TMJ",
         "port":"JPFKY",
         "portindex":4,
         "tankcategory":"WB",
         "tankname":"NO.4 WATER BALLAST TANK (P)",
         "volincube":0,
         "vesselcode":"PMM",
         "density":1.025,
         "capacity":2734.3,
         "weight":0,
         "lcglpp":87.86,
         "vcgbl":0,
         "tcgcl":-9.85,
         "fsm":23005.4,
         "select":true,
         "maxper":100,
         "partialyfilled":false,
         "fullyfilled":false,
         "unpumpableweight":0,
         "holdtank":"N",
         "bmax":"false",
         "sounding":0,
         "volinpercent":0
      },
      {
         "scenarioid":"PMM MP 002 TMJ",
         "port":"JPFKY",
         "portindex":4,
         "tankcategory":"WB",
         "tankname":"NO.4 WATER BALLAST TANK (S)",
         "volincube":0,
         "vesselcode":"PMM",
         "density":1.025,
         "capacity":2734.3,
         "weight":0,
         "lcglpp":87.86,
         "vcgbl":0,
         "tcgcl":9.85,
         "fsm":23005.4,
         "select":true,
         "maxper":100,
         "partialyfilled":false,
         "fullyfilled":false,
         "unpumpableweight":0,
         "holdtank":"N",
         "bmax":"false",
         "sounding":0,
         "volinpercent":0
      },
      {
         "scenarioid":"PMM MP 002 TMJ",
         "port":"JPFKY",
         "portindex":4,
         "tankcategory":"WB",
         "tankname":"NO.5 WATER BALLAST TANK (P)",
         "volincube":0,
         "vesselcode":"PMM",
         "density":1.025,
         "capacity":2119.7,
         "weight":0,
         "lcglpp":53.6,
         "vcgbl":0,
         "tcgcl":-6.28,
         "fsm":6281.9,
         "select":true,
         "maxper":100,
         "partialyfilled":false,
         "fullyfilled":false,
         "unpumpableweight":0,
         "holdtank":"N",
         "bmax":"false",
         "sounding":0,
         "volinpercent":0
      },
      {
         "scenarioid":"PMM MP 002 TMJ",
         "port":"JPFKY",
         "portindex":4,
         "tankcategory":"WB",
         "tankname":"NO.5 WATER BALLAST TANK (S)",
         "volincube":0,
         "vesselcode":"PMM",
         "density":1.025,
         "capacity":2277.3,
         "weight":0,
         "lcglpp":53.41,
         "vcgbl":0,
         "tcgcl":6.25,
         "fsm":6338.8,
         "select":true,
         "maxper":100,
         "partialyfilled":false,
         "fullyfilled":false,
         "unpumpableweight":0,
         "holdtank":"N",
         "bmax":"false",
         "sounding":0,
         "volinpercent":0
      },
      {
         "scenarioid":"PMM MP 002 TMJ",
         "port":"JPFKY",
         "portindex":4,
         "tankcategory":"WB",
         "tankname":"NO.5 T. S. T. /COLL. TANK (P)",
         "volincube":0,
         "vesselcode":"PMM",
         "density":1.025,
         "capacity":519,
         "weight":0,
         "lcglpp":41.79,
         "vcgbl":12.32,
         "tcgcl":-20.76,
         "fsm":0.1,
         "select":true,
         "maxper":100,
         "partialyfilled":false,
         "fullyfilled":false,
         "unpumpableweight":0,
         "holdtank":"N",
         "bmax":"false",
         "sounding":0,
         "volinpercent":0
      },
      {
         "scenarioid":"PMM MP 002 TMJ",
         "port":"JPFKY",
         "portindex":4,
         "tankcategory":"WB",
         "tankname":"NO.5 T. S. T. /COLL. TANK (S)",
         "volincube":0,
         "vesselcode":"PMM",
         "density":1.025,
         "capacity":519,
         "weight":0,
         "lcglpp":41.79,
         "vcgbl":12.32,
         "tcgcl":20.76,
         "fsm":0.1,
         "select":true,
         "maxper":100,
         "partialyfilled":false,
         "fullyfilled":false,
         "unpumpableweight":0,
         "holdtank":"N",
         "bmax":"false",
         "sounding":0,
         "volinpercent":0
      },
      {
         "scenarioid":"PMM MP 002 TMJ",
         "port":"JPFKY",
         "portindex":4,
         "tankcategory":"WB",
         "tankname":"AFT PEAK TANK C",
         "volincube":0,
         "vesselcode":"PMM",
         "density":1.025,
         "capacity":1732.1,
         "weight":0,
         "lcglpp":9.19,
         "vcgbl":7.93,
         "tcgcl":0,
         "fsm":0.1,
         "select":true,
         "maxper":100,
         "partialyfilled":false,
         "fullyfilled":false,
         "unpumpableweight":0,
         "holdtank":"N",
         "bmax":"false",
         "sounding":0,
         "volinpercent":0
      },
      {
         "scenarioid":"PMM MP 002 TMJ",
         "port":"JPFKY",
         "portindex":4,
         "tankcategory":"WB",
         "tankname":"NO.3 HOLD (W.B)",
         "volincube":0,
         "vesselcode":"PMM",
         "density":1.025,
         "capacity":21509,
         "weight":0,
         "lcglpp":124.58,
         "vcgbl":2.07,
         "tcgcl":0,
         "fsm":85795.7,
         "select":true,
         "maxper":100,
         "partialyfilled":false,
         "fullyfilled":false,
         "unpumpableweight":0,
         "holdtank":"Y",
         "bmax":"false",
         "sounding":0,
         "volinpercent":0
      }
   ],
   "Tank":[
      {
         "scenarioid":"PMM MP 002 TMJ",
         "port":"AUNLT",
         "portindex":1,
         "tankcategory":"FO",
         "tankname":"NO.1 F. O./M. G. O.T. (P)",
         "volincube":2.58,
         "vesselcode":"PMM",
         "density":0.97,
         "capacity":237.6,
         "weight":2.5,
         "lcglpp":101.25,
         "vcgbl":14,
         "tcgcl":-18.56,
         "fsm":0.69,
         "select":false,
         "maxper":0,
         "partialyfilled":false,
         "fullyfilled":false,
         "unpumpableweight":0,
         "holdtank":"N",
         "bmax":"false",
         "sounding":0.52,
         "volinpercent":0.01
      },
      {
         "scenarioid":"PMM MP 002 TMJ",
         "port":"AUNLT",
         "portindex":1,
         "tankcategory":"FO",
         "tankname":"NO.2 FUEL OIL TANK (P)",
         "volincube":494.85,
         "vesselcode":"PMM",
         "density":0.97,
         "capacity":594,
         "weight":480,
         "lcglpp":82.03,
         "vcgbl":16.7,
         "tcgcl":-16.22,
         "fsm":1025.11,
         "select":false,
         "maxper":0,
         "partialyfilled":false,
         "fullyfilled":false,
         "unpumpableweight":0,
         "holdtank":"N",
         "bmax":"false",
         "sounding":4.59,
         "volinpercent":0.83
      },
      {
         "scenarioid":"PMM MP 002 TMJ",
         "port":"AUNLT",
         "portindex":1,
         "tankcategory":"FO",
         "tankname":"NO.2 F. O./M. G. O.T. (S)",
         "volincube":494.85,
         "vesselcode":"PMM",
         "density":0.97,
         "capacity":594,
         "weight":480,
         "lcglpp":82.03,
         "vcgbl":16.7,
         "tcgcl":16.22,
         "fsm":1025.11,
         "select":false,
         "maxper":0,
         "partialyfilled":false,
         "fullyfilled":false,
         "unpumpableweight":0,
         "holdtank":"N",
         "bmax":"false",
         "sounding":4.59,
         "volinpercent":0.83
      },
      {
         "scenarioid":"PMM MP 002 TMJ",
         "port":"AUNLT",
         "portindex":1,
         "tankcategory":"FO",
         "tankname":"NO.3 FUEL OIL TANK (P)",
         "volincube":10.31,
         "vesselcode":"PMM",
         "density":0.97,
         "capacity":829.7,
         "weight":10,
         "lcglpp":51.08,
         "vcgbl":14.04,
         "tcgcl":-18.52,
         "fsm":3.14,
         "select":false,
         "maxper":0,
         "partialyfilled":false,
         "fullyfilled":false,
         "unpumpableweight":0,
         "holdtank":"N",
         "bmax":"false",
         "sounding":0.59,
         "volinpercent":0.01
      },
      {
         "scenarioid":"PMM MP 002 TMJ",
         "port":"AUNLT",
         "portindex":1,
         "tankcategory":"FO",
         "tankname":"NO.3 FUEL OIL TANK (S)",
         "volincube":10.31,
         "vesselcode":"PMM",
         "density":0.97,
         "capacity":829.7,
         "weight":10,
         "lcglpp":51.08,
         "vcgbl":14.04,
         "tcgcl":18.52,
         "fsm":3.14,
         "select":false,
         "maxper":0,
         "partialyfilled":false,
         "fullyfilled":false,
         "unpumpableweight":0,
         "holdtank":"N",
         "bmax":"false",
         "sounding":0.59,
         "volinpercent":0.01
      },
      {
         "scenarioid":"PMM MP 002 TMJ",
         "port":"AUNLT",
         "portindex":1,
         "tankcategory":"DO",
         "tankname":"DIESEL OIL TANK (S)",
         "volincube":116.1,
         "vesselcode":"PMM",
         "density":0.86,
         "capacity":237.6,
         "weight":99.85,
         "lcglpp":101.25,
         "vcgbl":15.99,
         "tcgcl":16.83,
         "fsm":177.04,
         "select":false,
         "maxper":0,
         "partialyfilled":false,
         "fullyfilled":false,
         "unpumpableweight":0,
         "holdtank":"N",
         "bmax":"false",
         "sounding":3.51,
         "volinpercent":0.49
      },
      {
         "scenarioid":"PMM MP 002 TMJ",
         "port":"AUNLT",
         "portindex":1,
         "tankcategory":"FW",
         "tankname":"DRINKING WATER TANK (P)",
         "volincube":88,
         "vesselcode":"PMM",
         "density":1,
         "capacity":118.9,
         "weight":88,
         "lcglpp":15.23,
         "vcgbl":16.1,
         "tcgcl":-16.06,
         "fsm":139,
         "select":false,
         "maxper":0,
         "partialyfilled":false,
         "fullyfilled":false,
         "unpumpableweight":0,
         "holdtank":"N",
         "bmax":"false",
         "sounding":3.87,
         "volinpercent":0.74
      },
      {
         "scenarioid":"PMM MP 002 TMJ",
         "port":"AUNLT",
         "portindex":1,
         "tankcategory":"FW",
         "tankname":"NO. 1 FRESH WATER TANK (S)",
         "volincube":70,
         "vesselcode":"PMM",
         "density":1,
         "capacity":77.6,
         "weight":70,
         "lcglpp":11.46,
         "vcgbl":16.47,
         "tcgcl":15.48,
         "fsm":64.3,
         "select":false,
         "maxper":0,
         "partialyfilled":false,
         "fullyfilled":false,
         "unpumpableweight":0,
         "holdtank":"N",
         "bmax":"false",
         "sounding":4.34,
         "volinpercent":0.9
      },
      {
         "scenarioid":"PMM MP 002 TMJ",
         "port":"AUNLT",
         "portindex":1,
         "tankcategory":"FW",
         "tankname":"NO. 2 FRESH WATER TANK (P)",
         "volincube":100,
         "vesselcode":"PMM",
         "density":1,
         "capacity":253.5,
         "weight":100,
         "lcglpp":9.14,
         "vcgbl":15.4,
         "tcgcl":-11.7,
         "fsm":921.46,
         "select":false,
         "maxper":0,
         "partialyfilled":false,
         "fullyfilled":false,
         "unpumpableweight":0,
         "holdtank":"N",
         "bmax":"false",
         "sounding":2.33,
         "volinpercent":0.39
      },
      {
         "scenarioid":"PMM MP 002 TMJ",
         "port":"AUNLT",
         "portindex":1,
         "tankcategory":"WC",
         "tankname":"DEADWEIGHT CONSTANT",
         "volincube":348,
         "vesselcode":"PMM",
         "density":1,
         "capacity":348,
         "weight":348,
         "lcglpp":31.2,
         "vcgbl":11.09,
         "tcgcl":0,
         "fsm":0,
         "select":false,
         "maxper":0,
         "partialyfilled":false,
         "fullyfilled":false,
         "unpumpableweight":0,
         "holdtank":"N",
         "bmax":"0",
         "sounding":0,
         "volinpercent":0
      },
      {
         "scenarioid":"PMM MP 002 TMJ",
         "port":"AUGLT",
         "portindex":2,
         "tankcategory":"FO",
         "tankname":"NO.2 FUEL OIL TANK (P)",
         "volincube":448.68,
         "vesselcode":"PMM",
         "density":0.97,
         "capacity":594,
         "weight":435.22,
         "lcglpp":82.03,
         "vcgbl":16.56,
         "tcgcl":-16.34,
         "fsm":959.63,
         "select":false,
         "maxper":0,
         "partialyfilled":false,
         "fullyfilled":false,
         "unpumpableweight":0,
         "holdtank":"N",
         "bmax":"false",
         "sounding":4.37,
         "volinpercent":0.76
      },
      {
         "scenarioid":"PMM MP 002 TMJ",
         "port":"AUGLT",
         "portindex":2,
         "tankcategory":"FO",
         "tankname":"NO.2 F. O./M. G. O.T. (S)",
         "volincube":494.85,
         "vesselcode":"PMM",
         "density":0.97,
         "capacity":594,
         "weight":480,
         "lcglpp":82.03,
         "vcgbl":16.7,
         "tcgcl":16.22,
         "fsm":1025.11,
         "select":false,
         "maxper":0,
         "partialyfilled":false,
         "fullyfilled":false,
         "unpumpableweight":0,
         "holdtank":"N",
         "bmax":"false",
         "sounding":4.59,
         "volinpercent":0.83
      },
      {
         "scenarioid":"PMM MP 002 TMJ",
         "port":"AUGLT",
         "portindex":2,
         "tankcategory":"FO",
         "tankname":"NO.3 FUEL OIL TANK (P)",
         "volincube":10.31,
         "vesselcode":"PMM",
         "density":0.97,
         "capacity":829.7,
         "weight":10,
         "lcglpp":51.08,
         "vcgbl":14.04,
         "tcgcl":-18.52,
         "fsm":3.14,
         "select":false,
         "maxper":0,
         "partialyfilled":false,
         "fullyfilled":false,
         "unpumpableweight":0,
         "holdtank":"N",
         "bmax":"false",
         "sounding":0.59,
         "volinpercent":0.01
      },
      {
         "scenarioid":"PMM MP 002 TMJ",
         "port":"AUGLT",
         "portindex":2,
         "tankcategory":"FO",
         "tankname":"NO.3 FUEL OIL TANK (S)",
         "volincube":10.31,
         "vesselcode":"PMM",
         "density":0.97,
         "capacity":829.7,
         "weight":10,
         "lcglpp":51.08,
         "vcgbl":14.04,
         "tcgcl":18.52,
         "fsm":3.14,
         "select":false,
         "maxper":0,
         "partialyfilled":false,
         "fullyfilled":false,
         "unpumpableweight":0,
         "holdtank":"N",
         "bmax":"false",
         "sounding":0.59,
         "volinpercent":0.01
      },
      {
         "scenarioid":"PMM MP 002 TMJ",
         "port":"AUGLT",
         "portindex":2,
         "tankcategory":"DO",
         "tankname":"DIESEL OIL TANK (S)",
         "volincube":115.75,
         "vesselcode":"PMM",
         "density":0.86,
         "capacity":237.6,
         "weight":99.54,
         "lcglpp":101.25,
         "vcgbl":15.99,
         "tcgcl":16.84,
         "fsm":176.21,
         "select":false,
         "maxper":0,
         "partialyfilled":false,
         "fullyfilled":false,
         "unpumpableweight":0,
         "holdtank":"N",
         "bmax":"false",
         "sounding":3.51,
         "volinpercent":0.49
      },
      {
         "scenarioid":"PMM MP 002 TMJ",
         "port":"AUGLT",
         "portindex":2,
         "tankcategory":"FW",
         "tankname":"DRINKING WATER TANK (P)",
         "volincube":85.38,
         "vesselcode":"PMM",
         "density":1,
         "capacity":118.9,
         "weight":85.38,
         "lcglpp":15.23,
         "vcgbl":16.05,
         "tcgcl":-16.05,
         "fsm":138.37,
         "select":false,
         "maxper":0,
         "partialyfilled":false,
         "fullyfilled":false,
         "unpumpableweight":0,
         "holdtank":"N",
         "bmax":"false",
         "sounding":3.78,
         "volinpercent":0.72
      },
      {
         "scenarioid":"PMM MP 002 TMJ",
         "port":"AUGLT",
         "portindex":2,
         "tankcategory":"FW",
         "tankname":"NO. 1 FRESH WATER TANK (S)",
         "volincube":70,
         "vesselcode":"PMM",
         "density":1,
         "capacity":77.6,
         "weight":70,
         "lcglpp":11.46,
         "vcgbl":16.47,
         "tcgcl":15.48,
         "fsm":64.3,
         "select":false,
         "maxper":0,
         "partialyfilled":false,
         "fullyfilled":false,
         "unpumpableweight":0,
         "holdtank":"N",
         "bmax":"false",
         "sounding":4.34,
         "volinpercent":0.9
      },
      {
         "scenarioid":"PMM MP 002 TMJ",
         "port":"AUGLT",
         "portindex":2,
         "tankcategory":"FW",
         "tankname":"NO. 2 FRESH WATER TANK (P)",
         "volincube":100,
         "vesselcode":"PMM",
         "density":1,
         "capacity":253.5,
         "weight":100,
         "lcglpp":9.14,
         "vcgbl":15.4,
         "tcgcl":-11.7,
         "fsm":921.46,
         "select":false,
         "maxper":0,
         "partialyfilled":false,
         "fullyfilled":false,
         "unpumpableweight":0,
         "holdtank":"N",
         "bmax":"false",
         "sounding":2.33,
         "volinpercent":0.39
      },
      {
         "scenarioid":"PMM MP 002 TMJ",
         "port":"AUGLT",
         "portindex":2,
         "tankcategory":"WC",
         "tankname":"DEADWEIGHT CONSTANT",
         "volincube":348,
         "vesselcode":"PMM",
         "density":1,
         "capacity":348,
         "weight":348,
         "lcglpp":31.2,
         "vcgbl":11.09,
         "tcgcl":0,
         "fsm":0,
         "select":false,
         "maxper":0,
         "partialyfilled":false,
         "fullyfilled":false,
         "unpumpableweight":0,
         "holdtank":"N",
         "bmax":"0",
         "sounding":0,
         "volinpercent":0
      },
      {
         "scenarioid":"PMM MP 002 TMJ",
         "port":"JPKWS",
         "portindex":3,
         "tankcategory":"FO",
         "tankname":"NO.2 FUEL OIL TANK (P)",
         "volincube":89.89,
         "vesselcode":"PMM",
         "density":0.97,
         "capacity":594,
         "weight":87.19,
         "lcglpp":82.03,
         "vcgbl":14.95,
         "tcgcl":-17.73,
         "fsm":86.14,
         "select":false,
         "maxper":0,
         "partialyfilled":false,
         "fullyfilled":false,
         "unpumpableweight":0,
         "holdtank":"N",
         "bmax":"false",
         "sounding":1.95,
         "volinpercent":0.15
      },
      {
         "scenarioid":"PMM MP 002 TMJ",
         "port":"JPKWS",
         "portindex":3,
         "tankcategory":"FO",
         "tankname":"NO.2 F. O./M. G. O.T. (S)",
         "volincube":494.85,
         "vesselcode":"PMM",
         "density":0.97,
         "capacity":594,
         "weight":480,
         "lcglpp":82.03,
         "vcgbl":16.7,
         "tcgcl":16.22,
         "fsm":1025.11,
         "select":false,
         "maxper":0,
         "partialyfilled":false,
         "fullyfilled":false,
         "unpumpableweight":0,
         "holdtank":"N",
         "bmax":"false",
         "sounding":4.59,
         "volinpercent":0.83
      },
      {
         "scenarioid":"PMM MP 002 TMJ",
         "port":"JPKWS",
         "portindex":3,
         "tankcategory":"FO",
         "tankname":"NO.3 FUEL OIL TANK (P)",
         "volincube":10.31,
         "vesselcode":"PMM",
         "density":0.97,
         "capacity":829.7,
         "weight":10,
         "lcglpp":51.08,
         "vcgbl":14.04,
         "tcgcl":-18.52,
         "fsm":3.14,
         "select":false,
         "maxper":0,
         "partialyfilled":false,
         "fullyfilled":false,
         "unpumpableweight":0,
         "holdtank":"N",
         "bmax":"false",
         "sounding":0.59,
         "volinpercent":0.01
      },
      {
         "scenarioid":"PMM MP 002 TMJ",
         "port":"JPKWS",
         "portindex":3,
         "tankcategory":"FO",
         "tankname":"NO.3 FUEL OIL TANK (S)",
         "volincube":10.31,
         "vesselcode":"PMM",
         "density":0.97,
         "capacity":829.7,
         "weight":10,
         "lcglpp":51.08,
         "vcgbl":14.04,
         "tcgcl":18.52,
         "fsm":3.14,
         "select":false,
         "maxper":0,
         "partialyfilled":false,
         "fullyfilled":false,
         "unpumpableweight":0,
         "holdtank":"N",
         "bmax":"false",
         "sounding":0.59,
         "volinpercent":0.01
      },
      {
         "scenarioid":"PMM MP 002 TMJ",
         "port":"JPKWS",
         "portindex":3,
         "tankcategory":"DO",
         "tankname":"DIESEL OIL TANK (S)",
         "volincube":114.02,
         "vesselcode":"PMM",
         "density":0.86,
         "capacity":237.6,
         "weight":98.06,
         "lcglpp":101.25,
         "vcgbl":15.97,
         "tcgcl":16.85,
         "fsm":172.3,
         "select":false,
         "maxper":0,
         "partialyfilled":false,
         "fullyfilled":false,
         "unpumpableweight":0,
         "holdtank":"N",
         "bmax":"false",
         "sounding":3.48,
         "volinpercent":0.48
      },
      {
         "scenarioid":"PMM MP 002 TMJ",
         "port":"JPKWS",
         "portindex":3,
         "tankcategory":"FW",
         "tankname":"DRINKING WATER TANK (P)",
         "volincube":85.38,
         "vesselcode":"PMM",
         "density":1,
         "capacity":118.9,
         "weight":85.38,
         "lcglpp":15.23,
         "vcgbl":16.05,
         "tcgcl":-16.05,
         "fsm":138.37,
         "select":false,
         "maxper":0,
         "partialyfilled":false,
         "fullyfilled":false,
         "unpumpableweight":0,
         "holdtank":"N",
         "bmax":"false",
         "sounding":3.78,
         "volinpercent":0.72
      },
      {
         "scenarioid":"PMM MP 002 TMJ",
         "port":"JPKWS",
         "portindex":3,
         "tankcategory":"FW",
         "tankname":"NO. 1 FRESH WATER TANK (S)",
         "volincube":70,
         "vesselcode":"PMM",
         "density":1,
         "capacity":77.6,
         "weight":70,
         "lcglpp":11.46,
         "vcgbl":16.47,
         "tcgcl":15.48,
         "fsm":64.3,
         "select":false,
         "maxper":0,
         "partialyfilled":false,
         "fullyfilled":false,
         "unpumpableweight":0,
         "holdtank":"N",
         "bmax":"false",
         "sounding":4.34,
         "volinpercent":0.9
      },
      {
         "scenarioid":"PMM MP 002 TMJ",
         "port":"JPKWS",
         "portindex":3,
         "tankcategory":"FW",
         "tankname":"NO. 2 FRESH WATER TANK (P)",
         "volincube":100,
         "vesselcode":"PMM",
         "density":1,
         "capacity":253.5,
         "weight":100,
         "lcglpp":9.14,
         "vcgbl":15.4,
         "tcgcl":-11.7,
         "fsm":921.46,
         "select":false,
         "maxper":0,
         "partialyfilled":false,
         "fullyfilled":false,
         "unpumpableweight":0,
         "holdtank":"N",
         "bmax":"false",
         "sounding":2.33,
         "volinpercent":0.39
      },
      {
         "scenarioid":"PMM MP 002 TMJ",
         "port":"JPKWS",
         "portindex":3,
         "tankcategory":"WC",
         "tankname":"DEADWEIGHT CONSTANT",
         "volincube":348,
         "vesselcode":"PMM",
         "density":1,
         "capacity":348,
         "weight":348,
         "lcglpp":31.2,
         "vcgbl":11.09,
         "tcgcl":0,
         "fsm":0,
         "select":false,
         "maxper":0,
         "partialyfilled":false,
         "fullyfilled":false,
         "unpumpableweight":0,
         "holdtank":"N",
         "bmax":"0",
         "sounding":0,
         "volinpercent":0
      },
      {
         "scenarioid":"PMM MP 002 TMJ",
         "port":"JPFKY",
         "portindex":4,
         "tankcategory":"FO",
         "tankname":"NO.2 FUEL OIL TANK (P)",
         "volincube":40.49,
         "vesselcode":"PMM",
         "density":0.97,
         "capacity":594,
         "weight":39.28,
         "lcglpp":82.03,
         "vcgbl":14.53,
         "tcgcl":-18.1,
         "fsm":26.03,
         "select":false,
         "maxper":0,
         "partialyfilled":false,
         "fullyfilled":false,
         "unpumpableweight":0,
         "holdtank":"N",
         "bmax":"false",
         "sounding":1.31,
         "volinpercent":0.07
      },
      {
         "scenarioid":"PMM MP 002 TMJ",
         "port":"JPFKY",
         "portindex":4,
         "tankcategory":"FO",
         "tankname":"NO.2 F. O./M. G. O.T. (S)",
         "volincube":494.85,
         "vesselcode":"PMM",
         "density":0.97,
         "capacity":594,
         "weight":480,
         "lcglpp":82.03,
         "vcgbl":16.7,
         "tcgcl":16.22,
         "fsm":1025.11,
         "select":false,
         "maxper":0,
         "partialyfilled":false,
         "fullyfilled":false,
         "unpumpableweight":0,
         "holdtank":"N",
         "bmax":"false",
         "sounding":4.59,
         "volinpercent":0.83
      },
      {
         "scenarioid":"PMM MP 002 TMJ",
         "port":"JPFKY",
         "portindex":4,
         "tankcategory":"FO",
         "tankname":"NO.3 FUEL OIL TANK (P)",
         "volincube":10.31,
         "vesselcode":"PMM",
         "density":0.97,
         "capacity":829.7,
         "weight":10,
         "lcglpp":51.08,
         "vcgbl":14.04,
         "tcgcl":-18.52,
         "fsm":3.14,
         "select":false,
         "maxper":0,
         "partialyfilled":false,
         "fullyfilled":false,
         "unpumpableweight":0,
         "holdtank":"N",
         "bmax":"false",
         "sounding":0.59,
         "volinpercent":0.01
      },
      {
         "scenarioid":"PMM MP 002 TMJ",
         "port":"JPFKY",
         "portindex":4,
         "tankcategory":"FO",
         "tankname":"NO.3 FUEL OIL TANK (S)",
         "volincube":10.31,
         "vesselcode":"PMM",
         "density":0.97,
         "capacity":829.7,
         "weight":10,
         "lcglpp":51.08,
         "vcgbl":14.04,
         "tcgcl":18.52,
         "fsm":3.14,
         "select":false,
         "maxper":0,
         "partialyfilled":false,
         "fullyfilled":false,
         "unpumpableweight":0,
         "holdtank":"N",
         "bmax":"false",
         "sounding":0.59,
         "volinpercent":0.01
      },
      {
         "scenarioid":"PMM MP 002 TMJ",
         "port":"JPFKY",
         "portindex":4,
         "tankcategory":"DO",
         "tankname":"DIESEL OIL TANK (S)",
         "volincube":113.8,
         "vesselcode":"PMM",
         "density":0.86,
         "capacity":237.6,
         "weight":97.87,
         "lcglpp":101.25,
         "vcgbl":15.97,
         "tcgcl":16.85,
         "fsm":171.82,
         "select":false,
         "maxper":0,
         "partialyfilled":false,
         "fullyfilled":false,
         "unpumpableweight":0,
         "holdtank":"N",
         "bmax":"false",
         "sounding":3.48,
         "volinpercent":0.48
      },
      {
         "scenarioid":"PMM MP 002 TMJ",
         "port":"JPFKY",
         "portindex":4,
         "tankcategory":"FW",
         "tankname":"DRINKING WATER TANK (P)",
         "volincube":85.38,
         "vesselcode":"PMM",
         "density":1,
         "capacity":118.9,
         "weight":85.38,
         "lcglpp":15.23,
         "vcgbl":16.05,
         "tcgcl":-16.05,
         "fsm":138.37,
         "select":false,
         "maxper":0,
         "partialyfilled":false,
         "fullyfilled":false,
         "unpumpableweight":0,
         "holdtank":"N",
         "bmax":"false",
         "sounding":3.78,
         "volinpercent":0.72
      },
      {
         "scenarioid":"PMM MP 002 TMJ",
         "port":"JPFKY",
         "portindex":4,
         "tankcategory":"FW",
         "tankname":"NO. 1 FRESH WATER TANK (S)",
         "volincube":70,
         "vesselcode":"PMM",
         "density":1,
         "capacity":77.6,
         "weight":70,
         "lcglpp":11.46,
         "vcgbl":16.47,
         "tcgcl":15.48,
         "fsm":64.3,
         "select":false,
         "maxper":0,
         "partialyfilled":false,
         "fullyfilled":false,
         "unpumpableweight":0,
         "holdtank":"N",
         "bmax":"false",
         "sounding":4.34,
         "volinpercent":0.9
      },
      {
         "scenarioid":"PMM MP 002 TMJ",
         "port":"JPFKY",
         "portindex":4,
         "tankcategory":"FW",
         "tankname":"NO. 2 FRESH WATER TANK (P)",
         "volincube":100,
         "vesselcode":"PMM",
         "density":1,
         "capacity":253.5,
         "weight":100,
         "lcglpp":9.14,
         "vcgbl":15.4,
         "tcgcl":-11.7,
         "fsm":921.46,
         "select":false,
         "maxper":0,
         "partialyfilled":false,
         "fullyfilled":false,
         "unpumpableweight":0,
         "holdtank":"N",
         "bmax":"false",
         "sounding":2.33,
         "volinpercent":0.39
      },
      {
         "scenarioid":"PMM MP 002 TMJ",
         "port":"JPFKY",
         "portindex":4,
         "tankcategory":"WC",
         "tankname":"DEADWEIGHT CONSTANT",
         "volincube":348,
         "vesselcode":"PMM",
         "density":1,
         "capacity":348,
         "weight":348,
         "lcglpp":31.2,
         "vcgbl":11.09,
         "tcgcl":0,
         "fsm":0,
         "select":false,
         "maxper":0,
         "partialyfilled":false,
         "fullyfilled":false,
         "unpumpableweight":0,
         "holdtank":"N",
         "bmax":"0",
         "sounding":0,
         "volinpercent":0
      }
   ],
   "ArrivalTank":[
      {
         "scenarioid":"PMM MP 002 TMJ",
         "port":"AUNLT",
         "portindex":1,
         "tankcategory":"FO",
         "tankname":"NO.1 F. O./M. G. O.T. (P)",
         "volincube":10.31,
         "vesselcode":"PMM",
         "density":0.97,
         "capacity":237.6,
         "weight":10,
         "lcglpp":101.25,
         "vcgbl":14.35,
         "tcgcl":-18.26,
         "fsm":5.28,
         "select":false,
         "maxper":0,
         "partialyfilled":false,
         "fullyfilled":false,
         "unpumpableweight":0,
         "holdtank":"N",
         "bmax":"false",
         "sounding":1.05,
         "volinpercent":0.04
      },
      {
         "scenarioid":"PMM MP 002 TMJ",
         "port":"AUNLT",
         "portindex":1,
         "tankcategory":"FO",
         "tankname":"NO.2 FUEL OIL TANK (P)",
         "volincube":494.85,
         "vesselcode":"PMM",
         "density":0.97,
         "capacity":594,
         "weight":480,
         "lcglpp":82.03,
         "vcgbl":16.7,
         "tcgcl":-16.22,
         "fsm":1025.11,
         "select":false,
         "maxper":0,
         "partialyfilled":false,
         "fullyfilled":false,
         "unpumpableweight":0,
         "holdtank":"N",
         "bmax":"false",
         "sounding":4.59,
         "volinpercent":0.83
      },
      {
         "scenarioid":"PMM MP 002 TMJ",
         "port":"AUNLT",
         "portindex":1,
         "tankcategory":"FO",
         "tankname":"NO.2 F. O./M. G. O.T. (S)",
         "volincube":494.85,
         "vesselcode":"PMM",
         "density":0.97,
         "capacity":594,
         "weight":480,
         "lcglpp":82.03,
         "vcgbl":16.7,
         "tcgcl":16.22,
         "fsm":1025.11,
         "select":false,
         "maxper":0,
         "partialyfilled":false,
         "fullyfilled":false,
         "unpumpableweight":0,
         "holdtank":"N",
         "bmax":"false",
         "sounding":4.59,
         "volinpercent":0.83
      },
      {
         "scenarioid":"PMM MP 002 TMJ",
         "port":"AUNLT",
         "portindex":1,
         "tankcategory":"FO",
         "tankname":"NO.3 FUEL OIL TANK (P)",
         "volincube":10.31,
         "vesselcode":"PMM",
         "density":0.97,
         "capacity":829.7,
         "weight":10,
         "lcglpp":51.08,
         "vcgbl":14.04,
         "tcgcl":-18.52,
         "fsm":3.14,
         "select":false,
         "maxper":0,
         "partialyfilled":false,
         "fullyfilled":false,
         "unpumpableweight":0,
         "holdtank":"N",
         "bmax":"false",
         "sounding":0.59,
         "volinpercent":0.01
      },
      {
         "scenarioid":"PMM MP 002 TMJ",
         "port":"AUNLT",
         "portindex":1,
         "tankcategory":"FO",
         "tankname":"NO.3 FUEL OIL TANK (S)",
         "volincube":10.31,
         "vesselcode":"PMM",
         "density":0.97,
         "capacity":829.7,
         "weight":10,
         "lcglpp":51.08,
         "vcgbl":14.04,
         "tcgcl":18.52,
         "fsm":3.14,
         "select":false,
         "maxper":0,
         "partialyfilled":false,
         "fullyfilled":false,
         "unpumpableweight":0,
         "holdtank":"N",
         "bmax":"false",
         "sounding":0.59,
         "volinpercent":0.01
      },
      {
         "scenarioid":"PMM MP 002 TMJ",
         "port":"AUNLT",
         "portindex":1,
         "tankcategory":"DO",
         "tankname":"DIESEL OIL TANK (S)",
         "volincube":116.28,
         "vesselcode":"PMM",
         "density":0.86,
         "capacity":237.6,
         "weight":100,
         "lcglpp":101.25,
         "vcgbl":15.99,
         "tcgcl":16.83,
         "fsm":177.44,
         "select":false,
         "maxper":0,
         "partialyfilled":false,
         "fullyfilled":false,
         "unpumpableweight":0,
         "holdtank":"N",
         "bmax":"false",
         "sounding":3.52,
         "volinpercent":0.49
      },
      {
         "scenarioid":"PMM MP 002 TMJ",
         "port":"AUNLT",
         "portindex":1,
         "tankcategory":"FW",
         "tankname":"DRINKING WATER TANK (P)",
         "volincube":100,
         "vesselcode":"PMM",
         "density":1,
         "capacity":118.9,
         "weight":100,
         "lcglpp":15.23,
         "vcgbl":16.3,
         "tcgcl":-16.1,
         "fsm":140.47,
         "select":false,
         "maxper":0,
         "partialyfilled":false,
         "fullyfilled":false,
         "unpumpableweight":0,
         "holdtank":"N",
         "bmax":"false",
         "sounding":4.27,
         "volinpercent":0.84
      },
      {
         "scenarioid":"PMM MP 002 TMJ",
         "port":"AUNLT",
         "portindex":1,
         "tankcategory":"FW",
         "tankname":"NO. 1 FRESH WATER TANK (S)",
         "volincube":70,
         "vesselcode":"PMM",
         "density":1,
         "capacity":77.6,
         "weight":70,
         "lcglpp":11.46,
         "vcgbl":16.47,
         "tcgcl":15.48,
         "fsm":64.3,
         "select":false,
         "maxper":0,
         "partialyfilled":false,
         "fullyfilled":false,
         "unpumpableweight":0,
         "holdtank":"N",
         "bmax":"false",
         "sounding":4.34,
         "volinpercent":0.9
      },
      {
         "scenarioid":"PMM MP 002 TMJ",
         "port":"AUNLT",
         "portindex":1,
         "tankcategory":"FW",
         "tankname":"NO. 2 FRESH WATER TANK (P)",
         "volincube":100,
         "vesselcode":"PMM",
         "density":1,
         "capacity":253.5,
         "weight":100,
         "lcglpp":9.14,
         "vcgbl":15.4,
         "tcgcl":-11.7,
         "fsm":921.46,
         "select":false,
         "maxper":0,
         "partialyfilled":false,
         "fullyfilled":false,
         "unpumpableweight":0,
         "holdtank":"N",
         "bmax":"false",
         "sounding":2.33,
         "volinpercent":0.39
      },
      {
         "scenarioid":"PMM MP 002 TMJ",
         "port":"AUNLT",
         "portindex":1,
         "tankcategory":"WC",
         "tankname":"DEADWEIGHT CONSTANT",
         "volincube":348,
         "vesselcode":"PMM",
         "density":1,
         "capacity":348,
         "weight":348,
         "lcglpp":31.2,
         "vcgbl":11.09,
         "tcgcl":0,
         "fsm":0,
         "select":false,
         "maxper":0,
         "partialyfilled":false,
         "fullyfilled":false,
         "unpumpableweight":0,
         "holdtank":"N",
         "bmax":"0",
         "sounding":0,
         "volinpercent":0
      },
      {
         "scenarioid":"PMM MP 002 TMJ",
         "port":"AUGLT",
         "portindex":2,
         "tankcategory":"FO",
         "tankname":"NO.2 FUEL OIL TANK (P)",
         "volincube":456.41,
         "vesselcode":"PMM",
         "density":0.97,
         "capacity":594,
         "weight":442.72,
         "lcglpp":82.03,
         "vcgbl":16.58,
         "tcgcl":-16.32,
         "fsm":984.33,
         "select":false,
         "maxper":0,
         "partialyfilled":false,
         "fullyfilled":false,
         "unpumpableweight":0,
         "holdtank":"N",
         "bmax":"false",
         "sounding":4.4,
         "volinpercent":0.77
      },
      {
         "scenarioid":"PMM MP 002 TMJ",
         "port":"AUGLT",
         "portindex":2,
         "tankcategory":"FO",
         "tankname":"NO.2 F. O./M. G. O.T. (S)",
         "volincube":494.85,
         "vesselcode":"PMM",
         "density":0.97,
         "capacity":594,
         "weight":480,
         "lcglpp":82.03,
         "vcgbl":16.7,
         "tcgcl":16.22,
         "fsm":1025.11,
         "select":false,
         "maxper":0,
         "partialyfilled":false,
         "fullyfilled":false,
         "unpumpableweight":0,
         "holdtank":"N",
         "bmax":"false",
         "sounding":4.59,
         "volinpercent":0.83
      },
      {
         "scenarioid":"PMM MP 002 TMJ",
         "port":"AUGLT",
         "portindex":2,
         "tankcategory":"FO",
         "tankname":"NO.3 FUEL OIL TANK (P)",
         "volincube":10.31,
         "vesselcode":"PMM",
         "density":0.97,
         "capacity":829.7,
         "weight":10,
         "lcglpp":51.08,
         "vcgbl":14.04,
         "tcgcl":-18.52,
         "fsm":3.14,
         "select":false,
         "maxper":0,
         "partialyfilled":false,
         "fullyfilled":false,
         "unpumpableweight":0,
         "holdtank":"N",
         "bmax":"false",
         "sounding":0.59,
         "volinpercent":0.01
      },
      {
         "scenarioid":"PMM MP 002 TMJ",
         "port":"AUGLT",
         "portindex":2,
         "tankcategory":"FO",
         "tankname":"NO.3 FUEL OIL TANK (S)",
         "volincube":10.31,
         "vesselcode":"PMM",
         "density":0.97,
         "capacity":829.7,
         "weight":10,
         "lcglpp":51.08,
         "vcgbl":14.04,
         "tcgcl":18.52,
         "fsm":3.14,
         "select":false,
         "maxper":0,
         "partialyfilled":false,
         "fullyfilled":false,
         "unpumpableweight":0,
         "holdtank":"N",
         "bmax":"false",
         "sounding":0.59,
         "volinpercent":0.01
      },
      {
         "scenarioid":"PMM MP 002 TMJ",
         "port":"AUGLT",
         "portindex":2,
         "tankcategory":"DO",
         "tankname":"DIESEL OIL TANK (S)",
         "volincube":115.92,
         "vesselcode":"PMM",
         "density":0.86,
         "capacity":237.6,
         "weight":99.69,
         "lcglpp":101.25,
         "vcgbl":15.99,
         "tcgcl":16.83,
         "fsm":176.62,
         "select":false,
         "maxper":0,
         "partialyfilled":false,
         "fullyfilled":false,
         "unpumpableweight":0,
         "holdtank":"N",
         "bmax":"false",
         "sounding":3.51,
         "volinpercent":0.49
      },
      {
         "scenarioid":"PMM MP 002 TMJ",
         "port":"AUGLT",
         "portindex":2,
         "tankcategory":"FW",
         "tankname":"DRINKING WATER TANK (P)",
         "volincube":97.38,
         "vesselcode":"PMM",
         "density":1,
         "capacity":118.9,
         "weight":97.38,
         "lcglpp":15.23,
         "vcgbl":16.26,
         "tcgcl":-16.09,
         "fsm":140.36,
         "select":false,
         "maxper":0,
         "partialyfilled":false,
         "fullyfilled":false,
         "unpumpableweight":0,
         "holdtank":"N",
         "bmax":"false",
         "sounding":4.18,
         "volinpercent":0.82
      },
      {
         "scenarioid":"PMM MP 002 TMJ",
         "port":"AUGLT",
         "portindex":2,
         "tankcategory":"FW",
         "tankname":"NO. 1 FRESH WATER TANK (S)",
         "volincube":70,
         "vesselcode":"PMM",
         "density":1,
         "capacity":77.6,
         "weight":70,
         "lcglpp":11.46,
         "vcgbl":16.47,
         "tcgcl":15.48,
         "fsm":64.3,
         "select":false,
         "maxper":0,
         "partialyfilled":false,
         "fullyfilled":false,
         "unpumpableweight":0,
         "holdtank":"N",
         "bmax":"false",
         "sounding":4.34,
         "volinpercent":0.9
      },
      {
         "scenarioid":"PMM MP 002 TMJ",
         "port":"AUGLT",
         "portindex":2,
         "tankcategory":"FW",
         "tankname":"NO. 2 FRESH WATER TANK (P)",
         "volincube":100,
         "vesselcode":"PMM",
         "density":1,
         "capacity":253.5,
         "weight":100,
         "lcglpp":9.14,
         "vcgbl":15.4,
         "tcgcl":-11.7,
         "fsm":921.46,
         "select":false,
         "maxper":0,
         "partialyfilled":false,
         "fullyfilled":false,
         "unpumpableweight":0,
         "holdtank":"N",
         "bmax":"false",
         "sounding":2.33,
         "volinpercent":0.39
      },
      {
         "scenarioid":"PMM MP 002 TMJ",
         "port":"AUGLT",
         "portindex":2,
         "tankcategory":"WC",
         "tankname":"DEADWEIGHT CONSTANT",
         "volincube":348,
         "vesselcode":"PMM",
         "density":1,
         "capacity":348,
         "weight":348,
         "lcglpp":31.2,
         "vcgbl":11.09,
         "tcgcl":0,
         "fsm":0,
         "select":false,
         "maxper":0,
         "partialyfilled":false,
         "fullyfilled":false,
         "unpumpableweight":0,
         "holdtank":"N",
         "bmax":"0",
         "sounding":0,
         "volinpercent":0
      },
      {
         "scenarioid":"PMM MP 002 TMJ",
         "port":"JPKWS",
         "portindex":3,
         "tankcategory":"FO",
         "tankname":"NO.2 FUEL OIL TANK (P)",
         "volincube":97.62,
         "vesselcode":"PMM",
         "density":0.97,
         "capacity":594,
         "weight":94.69,
         "lcglpp":82.03,
         "vcgbl":15.01,
         "tcgcl":-17.69,
         "fsm":97.49,
         "select":false,
         "maxper":0,
         "partialyfilled":false,
         "fullyfilled":false,
         "unpumpableweight":0,
         "holdtank":"N",
         "bmax":"false",
         "sounding":2.04,
         "volinpercent":0.16
      },
      {
         "scenarioid":"PMM MP 002 TMJ",
         "port":"JPKWS",
         "portindex":3,
         "tankcategory":"FO",
         "tankname":"NO.2 F. O./M. G. O.T. (S)",
         "volincube":494.85,
         "vesselcode":"PMM",
         "density":0.97,
         "capacity":594,
         "weight":480,
         "lcglpp":82.03,
         "vcgbl":16.7,
         "tcgcl":16.22,
         "fsm":1025.11,
         "select":false,
         "maxper":0,
         "partialyfilled":false,
         "fullyfilled":false,
         "unpumpableweight":0,
         "holdtank":"N",
         "bmax":"false",
         "sounding":4.59,
         "volinpercent":0.83
      },
      {
         "scenarioid":"PMM MP 002 TMJ",
         "port":"JPKWS",
         "portindex":3,
         "tankcategory":"FO",
         "tankname":"NO.3 FUEL OIL TANK (P)",
         "volincube":10.31,
         "vesselcode":"PMM",
         "density":0.97,
         "capacity":829.7,
         "weight":10,
         "lcglpp":51.08,
         "vcgbl":14.04,
         "tcgcl":-18.52,
         "fsm":3.14,
         "select":false,
         "maxper":0,
         "partialyfilled":false,
         "fullyfilled":false,
         "unpumpableweight":0,
         "holdtank":"N",
         "bmax":"false",
         "sounding":0.59,
         "volinpercent":0.01
      },
      {
         "scenarioid":"PMM MP 002 TMJ",
         "port":"JPKWS",
         "portindex":3,
         "tankcategory":"FO",
         "tankname":"NO.3 FUEL OIL TANK (S)",
         "volincube":10.31,
         "vesselcode":"PMM",
         "density":0.97,
         "capacity":829.7,
         "weight":10,
         "lcglpp":51.08,
         "vcgbl":14.04,
         "tcgcl":18.52,
         "fsm":3.14,
         "select":false,
         "maxper":0,
         "partialyfilled":false,
         "fullyfilled":false,
         "unpumpableweight":0,
         "holdtank":"N",
         "bmax":"false",
         "sounding":0.59,
         "volinpercent":0.01
      },
      {
         "scenarioid":"PMM MP 002 TMJ",
         "port":"JPKWS",
         "portindex":3,
         "tankcategory":"DO",
         "tankname":"DIESEL OIL TANK (S)",
         "volincube":114.19,
         "vesselcode":"PMM",
         "density":0.86,
         "capacity":237.6,
         "weight":98.21,
         "lcglpp":101.25,
         "vcgbl":15.97,
         "tcgcl":16.85,
         "fsm":172.69,
         "select":false,
         "maxper":0,
         "partialyfilled":false,
         "fullyfilled":false,
         "unpumpableweight":0,
         "holdtank":"N",
         "bmax":"false",
         "sounding":3.48,
         "volinpercent":0.48
      },
      {
         "scenarioid":"PMM MP 002 TMJ",
         "port":"JPKWS",
         "portindex":3,
         "tankcategory":"FW",
         "tankname":"DRINKING WATER TANK (P)",
         "volincube":97.38,
         "vesselcode":"PMM",
         "density":1,
         "capacity":118.9,
         "weight":97.38,
         "lcglpp":15.23,
         "vcgbl":16.26,
         "tcgcl":-16.09,
         "fsm":140.36,
         "select":false,
         "maxper":0,
         "partialyfilled":false,
         "fullyfilled":false,
         "unpumpableweight":0,
         "holdtank":"N",
         "bmax":"false",
         "sounding":4.18,
         "volinpercent":0.82
      },
      {
         "scenarioid":"PMM MP 002 TMJ",
         "port":"JPKWS",
         "portindex":3,
         "tankcategory":"FW",
         "tankname":"NO. 1 FRESH WATER TANK (S)",
         "volincube":70,
         "vesselcode":"PMM",
         "density":1,
         "capacity":77.6,
         "weight":70,
         "lcglpp":11.46,
         "vcgbl":16.47,
         "tcgcl":15.48,
         "fsm":64.3,
         "select":false,
         "maxper":0,
         "partialyfilled":false,
         "fullyfilled":false,
         "unpumpableweight":0,
         "holdtank":"N",
         "bmax":"false",
         "sounding":4.34,
         "volinpercent":0.9
      },
      {
         "scenarioid":"PMM MP 002 TMJ",
         "port":"JPKWS",
         "portindex":3,
         "tankcategory":"FW",
         "tankname":"NO. 2 FRESH WATER TANK (P)",
         "volincube":100,
         "vesselcode":"PMM",
         "density":1,
         "capacity":253.5,
         "weight":100,
         "lcglpp":9.14,
         "vcgbl":15.4,
         "tcgcl":-11.7,
         "fsm":921.46,
         "select":false,
         "maxper":0,
         "partialyfilled":false,
         "fullyfilled":false,
         "unpumpableweight":0,
         "holdtank":"N",
         "bmax":"false",
         "sounding":2.33,
         "volinpercent":0.39
      },
      {
         "scenarioid":"PMM MP 002 TMJ",
         "port":"JPKWS",
         "portindex":3,
         "tankcategory":"WC",
         "tankname":"DEADWEIGHT CONSTANT",
         "volincube":348,
         "vesselcode":"PMM",
         "density":1,
         "capacity":348,
         "weight":348,
         "lcglpp":31.2,
         "vcgbl":11.09,
         "tcgcl":0,
         "fsm":0,
         "select":false,
         "maxper":0,
         "partialyfilled":false,
         "fullyfilled":false,
         "unpumpableweight":0,
         "holdtank":"N",
         "bmax":"0",
         "sounding":0,
         "volinpercent":0
      },
      {
         "scenarioid":"PMM MP 002 TMJ",
         "port":"JPFKY",
         "portindex":4,
         "tankcategory":"FO",
         "tankname":"NO.2 FUEL OIL TANK (P)",
         "volincube":40.49,
         "vesselcode":"PMM",
         "density":0.97,
         "capacity":594,
         "weight":39.28,
         "lcglpp":82.03,
         "vcgbl":14.53,
         "tcgcl":-18.1,
         "fsm":26.03,
         "select":false,
         "maxper":0,
         "partialyfilled":false,
         "fullyfilled":false,
         "unpumpableweight":0,
         "holdtank":"N",
         "bmax":"false",
         "sounding":1.31,
         "volinpercent":0.07
      },
      {
         "scenarioid":"PMM MP 002 TMJ",
         "port":"JPFKY",
         "portindex":4,
         "tankcategory":"FO",
         "tankname":"NO.2 F. O./M. G. O.T. (S)",
         "volincube":494.85,
         "vesselcode":"PMM",
         "density":0.97,
         "capacity":594,
         "weight":480,
         "lcglpp":82.03,
         "vcgbl":16.7,
         "tcgcl":16.22,
         "fsm":1025.11,
         "select":false,
         "maxper":0,
         "partialyfilled":false,
         "fullyfilled":false,
         "unpumpableweight":0,
         "holdtank":"N",
         "bmax":"false",
         "sounding":4.59,
         "volinpercent":0.83
      },
      {
         "scenarioid":"PMM MP 002 TMJ",
         "port":"JPFKY",
         "portindex":4,
         "tankcategory":"FO",
         "tankname":"NO.3 FUEL OIL TANK (P)",
         "volincube":10.31,
         "vesselcode":"PMM",
         "density":0.97,
         "capacity":829.7,
         "weight":10,
         "lcglpp":51.08,
         "vcgbl":14.04,
         "tcgcl":-18.52,
         "fsm":3.14,
         "select":false,
         "maxper":0,
         "partialyfilled":false,
         "fullyfilled":false,
         "unpumpableweight":0,
         "holdtank":"N",
         "bmax":"false",
         "sounding":0.59,
         "volinpercent":0.01
      },
      {
         "scenarioid":"PMM MP 002 TMJ",
         "port":"JPFKY",
         "portindex":4,
         "tankcategory":"FO",
         "tankname":"NO.3 FUEL OIL TANK (S)",
         "volincube":10.31,
         "vesselcode":"PMM",
         "density":0.97,
         "capacity":829.7,
         "weight":10,
         "lcglpp":51.08,
         "vcgbl":14.04,
         "tcgcl":18.52,
         "fsm":3.14,
         "select":false,
         "maxper":0,
         "partialyfilled":false,
         "fullyfilled":false,
         "unpumpableweight":0,
         "holdtank":"N",
         "bmax":"false",
         "sounding":0.59,
         "volinpercent":0.01
      },
      {
         "scenarioid":"PMM MP 002 TMJ",
         "port":"JPFKY",
         "portindex":4,
         "tankcategory":"DO",
         "tankname":"DIESEL OIL TANK (S)",
         "volincube":113.8,
         "vesselcode":"PMM",
         "density":0.86,
         "capacity":237.6,
         "weight":97.87,
         "lcglpp":101.25,
         "vcgbl":15.97,
         "tcgcl":16.85,
         "fsm":171.82,
         "select":false,
         "maxper":0,
         "partialyfilled":false,
         "fullyfilled":false,
         "unpumpableweight":0,
         "holdtank":"N",
         "bmax":"false",
         "sounding":3.48,
         "volinpercent":0.48
      },
      {
         "scenarioid":"PMM MP 002 TMJ",
         "port":"JPFKY",
         "portindex":4,
         "tankcategory":"FW",
         "tankname":"DRINKING WATER TANK (P)",
         "volincube":96.67,
         "vesselcode":"PMM",
         "density":1,
         "capacity":118.9,
         "weight":96.67,
         "lcglpp":15.23,
         "vcgbl":16.25,
         "tcgcl":-16.09,
         "fsm":140.31,
         "select":false,
         "maxper":0,
         "partialyfilled":false,
         "fullyfilled":false,
         "unpumpableweight":0,
         "holdtank":"N",
         "bmax":"false",
         "sounding":4.16,
         "volinpercent":0.81
      },
      {
         "scenarioid":"PMM MP 002 TMJ",
         "port":"JPFKY",
         "portindex":4,
         "tankcategory":"FW",
         "tankname":"NO. 1 FRESH WATER TANK (S)",
         "volincube":70,
         "vesselcode":"PMM",
         "density":1,
         "capacity":77.6,
         "weight":70,
         "lcglpp":11.46,
         "vcgbl":16.47,
         "tcgcl":15.48,
         "fsm":64.3,
         "select":false,
         "maxper":0,
         "partialyfilled":false,
         "fullyfilled":false,
         "unpumpableweight":0,
         "holdtank":"N",
         "bmax":"false",
         "sounding":4.34,
         "volinpercent":0.9
      },
      {
         "scenarioid":"PMM MP 002 TMJ",
         "port":"JPFKY",
         "portindex":4,
         "tankcategory":"FW",
         "tankname":"NO. 2 FRESH WATER TANK (P)",
         "volincube":100,
         "vesselcode":"PMM",
         "density":1,
         "capacity":253.5,
         "weight":100,
         "lcglpp":9.14,
         "vcgbl":15.4,
         "tcgcl":-11.7,
         "fsm":921.46,
         "select":false,
         "maxper":0,
         "partialyfilled":false,
         "fullyfilled":false,
         "unpumpableweight":0,
         "holdtank":"N",
         "bmax":"false",
         "sounding":2.33,
         "volinpercent":0.39
      },
      {
         "scenarioid":"PMM MP 002 TMJ",
         "port":"JPFKY",
         "portindex":4,
         "tankcategory":"WC",
         "tankname":"DEADWEIGHT CONSTANT",
         "volincube":348,
         "vesselcode":"PMM",
         "density":1,
         "capacity":348,
         "weight":348,
         "lcglpp":31.2,
         "vcgbl":11.09,
         "tcgcl":0,
         "fsm":0,
         "select":false,
         "maxper":0,
         "partialyfilled":false,
         "fullyfilled":false,
         "unpumpableweight":0,
         "holdtank":"N",
         "bmax":"0",
         "sounding":0,
         "volinpercent":0
      }
   ],
   "ChartedPartyAsswumption":[
      {
         "cargo":"coal",
         "techname":"coal",
         "grade":"A",
         "stowagefactor":39.859,
         "contract_qty":30000,
         "customer_request":0,
         "plusorminus":10,
         "pol":"AUNLT",
         "polIdx":1,
         "pol_terminal":"",
         "pol_berth":1,
         "pod":"JPFKY",
         "podIdx":4,
         "pod_terminal":"",
         "pod_berth":1,
         "terms":"MOLOO"
      },
      {
         "cargo":"COAL",
         "techname":"COAL",
         "grade":"B",
         "stowagefactor":40.845,
         "contract_qty":30000,
         "customer_request":0,
         "plusorminus":10,
         "pol":"AUGLT",
         "polIdx":2,
         "pol_terminal":"",
         "pol_berth":1,
         "pod":"JPKWS",
         "podIdx":3,
         "pod_terminal":"",
         "pod_berth":1,
         "terms":"MOLOO"
      },
      {
         "cargo":"COAL",
         "techname":"COAL",
         "grade":"B",
         "stowagefactor":40.845,
         "contract_qty":30000,
         "customer_request":0,
         "plusorminus":10,
         "pol":"AUGLT",
         "polIdx":2,
         "pol_terminal":"",
         "pol_berth":1,
         "pod":"JPFKY",
         "podIdx":4,
         "pod_terminal":"",
         "pod_berth":1,
         "terms":"MOLOO"
      }
   ],
   "UserAllocation":[
      
   ],
   "errorFlag":1,
   "BendingFlag":1,
   "stressflag":0,
   "VolumeFlag":1,
   "TrimFlag":1,
   "AdjacentCargoFlag":1,
   "chartedPartyFlag":1,
   "LoadableFlag":0,
   "weightFlag":1,
   "propellerFlag":0,
   "PreferedFlag":0,
   "mixedCargoFlag":1,
   "BallestTankWTFlag":0,
   "DeflectionFlag":0,
   "HatchCoverFlag":0,
   "FirstPass":1,
   "MinimumMassflag":0,
   "ArrivalDeaparture":1,
   "TrimConstFlag":0,
   "autoallocationFlag":1
}